datacontrol/__init__.py
datacontrol/qunat.py
datacontrol/textfill.py
DataControl-1.2.1.dist-info/LICENSE.txt
DataControl-1.2.1.dist-info/METADATA
DataControl-1.2.1.dist-info/WHEEL
DataControl-1.2.1.dist-info/top_level.txt
DataControl-1.2.1.dist-info/RECORD
