Metadata-Version: 2.1
Name: DataControl
Version: 1.2.1
Summary: Data governance script summary
Home-page: https://github.com/xxxxx/datacontrol
Author: CAIWEI
Author-email: caiwei@kuaishou.com
License: UNKNOWN
Project-URL: Bug Tracker, https://github.com/xxxxx/datacontrol/issues
Platform: UNKNOWN
Classifier: Programming Language :: Python :: 3
Classifier: License :: OSI Approved :: MIT License
Classifier: Operating System :: OS Independent
Requires-Python: >=3.6
License-File: LICENSE.txt
